literary_build_hatch/__init__.py
literary_build_hatch/hooks.py
literary_build_hatch/plugin.py
literary_build_hatch-0.3.0.dist-info/METADATA
literary_build_hatch-0.3.0.dist-info/WHEEL
literary_build_hatch-0.3.0.dist-info/entry_points.txt
literary_build_hatch-0.3.0.dist-info/RECORD
